talisman_dm-1.3.14.data/data/VERSION
tdm/__init__.py
tdm/model.py
tdm/abstract/__init__.py
tdm/abstract/datamodel/__init__.py
tdm/abstract/datamodel/document.py
tdm/abstract/datamodel/duplicatable.py
tdm/abstract/datamodel/filter.py
tdm/abstract/datamodel/identifiable.py
tdm/abstract/datamodel/mention.py
tdm/abstract/datamodel/node.py
tdm/abstract/datamodel/node_link.py
tdm/abstract/datamodel/value.py
tdm/abstract/datamodel/domain/__init__.py
tdm/abstract/datamodel/domain/_domain.py
tdm/abstract/datamodel/domain/_link.py
tdm/abstract/datamodel/domain/_type.py
tdm/abstract/datamodel/domain/_value.py
tdm/abstract/datamodel/fact/__init__.py
tdm/abstract/datamodel/fact/_fact.py
tdm/abstract/datamodel/fact/_link.py
tdm/abstract/datamodel/fact/_value.py
tdm/abstract/datamodel/markup/__init__.py
tdm/abstract/datamodel/markup/abstract.py
tdm/abstract/datamodel/markup/frozen.py
tdm/abstract/datamodel/markup/model.py
tdm/abstract/json_schema/__init__.py
tdm/abstract/json_schema/composite.py
tdm/abstract/json_schema/decorator.py
tdm/abstract/json_schema/model.py
tdm/abstract/json_schema/serializers/__init__.py
tdm/abstract/json_schema/serializers/abstract.py
tdm/abstract/json_schema/serializers/composite.py
tdm/abstract/json_schema/serializers/dataclass.py
tdm/abstract/json_schema/serializers/domain.py
tdm/abstract/json_schema/serializers/identifiable.py
tdm/abstract/json_schema/serializers/identity.py
tdm/abstract/json_schema/serializers/markup.py
tdm/abstract/json_schema/serializers/mention.py
tdm/abstract/json_schema/serializers/metadata.py
tdm/abstract/json_schema/serializers/serializers.py
tdm/abstract/json_schema/serializers/type_.py
tdm/abstract/json_schema/serializers/value.py
tdm/abstract/json_schema/serializers/wrap.py
tdm/datamodel/__init__.py
tdm/datamodel/common/__init__.py
tdm/datamodel/common/_container.py
tdm/datamodel/common/_impl.py
tdm/datamodel/common/_state.py
tdm/datamodel/common/_types.py
tdm/datamodel/common/_util.py
tdm/datamodel/common/_view.py
talisman_dm-1.3.14.dist-info/METADATA
talisman_dm-1.3.14.dist-info/WHEEL
talisman_dm-1.3.14.dist-info/top_level.txt
talisman_dm-1.3.14.dist-info/RECORD
