Metadata-Version: 2.1
Name: talisman-dm
Version: 1.3.14
Summary: Talisman Document Model python implementation
Home-page: https://gitlab.at.ispras.ru/talisman/core/talisman-tdm
Author: ISPRAS MODIS NLP team
Author-email: modis@ispras.ru
Maintainer: Vladimir Mayorov
Maintainer-email: vmayorov@ispras.ru
License: Apache Software License
Classifier: Development Status :: 3 - Alpha
Classifier: Programming Language :: Python :: 3
Classifier: Programming Language :: Python :: 3.7
Classifier: Intended Audience :: Developers
Classifier: Operating System :: OS Independent
Classifier: License :: OSI Approved :: Apache Software License
Requires-Python: >=3.7
Requires-Dist: pydantic~=2.5
Requires-Dist: typing-extensions>=4.0.1
Requires-Dist: immutabledict<3,>=2.2.4
